treams/sw.cpython-311-x86_64-linux-gnu.so
treams/_material.py
treams/_lattice.py
treams/misc.py
treams/_core.py
treams/pw.cpython-311-x86_64-linux-gnu.so
treams/_operators.py
treams/_tmatrix.py
treams/io.py
treams/util.py
treams/_smatrix.py
treams/cw.cpython-311-x86_64-linux-gnu.so
treams/coeffs.cpython-311-x86_64-linux-gnu.so
treams/ebcm.py
treams/__init__.py
treams/config.cpython-311-x86_64-linux-gnu.so
treams/special/cython_special.cpython-311-x86_64-linux-gnu.so
treams/special/_ufuncs.cpython-311-x86_64-linux-gnu.so
treams/special/_gufuncs.cpython-311-x86_64-linux-gnu.so
treams/special/_wigner3j.cpython-311-x86_64-linux-gnu.so
treams/special/_waves.cpython-311-x86_64-linux-gnu.so
treams/special/_misc.cpython-311-x86_64-linux-gnu.so
treams/special/_bessel.cpython-311-x86_64-linux-gnu.so
treams/special/_coord.cpython-311-x86_64-linux-gnu.so
treams/special/_wignerd.cpython-311-x86_64-linux-gnu.so
treams/special/_integrals.cpython-311-x86_64-linux-gnu.so
treams/special/__init__.py
treams/lattice/_gufuncs.cpython-311-x86_64-linux-gnu.so
treams/lattice/_misc.cpython-311-x86_64-linux-gnu.so
treams/lattice/_dsum.cpython-311-x86_64-linux-gnu.so
treams/lattice/cython_lattice.cpython-311-x86_64-linux-gnu.so
treams/lattice/_esum.cpython-311-x86_64-linux-gnu.so
treams/lattice/__init__.py
treams_dev-0.4.3.dist-info/LICENSE
treams_dev-0.4.3.dist-info/WHEEL
treams_dev-0.4.3.dist-info/top_level.txt
treams_dev-0.4.3.dist-info/RECORD
treams_dev-0.4.3.dist-info/METADATA
