Metadata-Version: 2.1
Name: treams-dev
Version: 0.4.3
Summary: "T-matrix scattering code for nanophotonic computations"
Home-page: https://github.com/tfp-photonics/treams
Author: Dominik Beutel
Author-email: dominik.beutel@kit.edu
License: MIT
Platform: Linux
Platform: Windows
Classifier: Development Status :: 4 - Beta
Classifier: Intended Audience :: Science/Research
Classifier: Operating System :: Microsoft :: Windows
Classifier: Operating System :: POSIX :: Linux
Classifier: Natural Language :: English
Classifier: Programming Language :: Python
Classifier: Programming Language :: Python :: 3
Classifier: Programming Language :: Python :: 3 :: Only
Classifier: Programming Language :: Python :: 3.8
Classifier: Programming Language :: Python :: 3.9
Classifier: Programming Language :: Python :: 3.10
Classifier: Programming Language :: Python :: 3.11
Classifier: Programming Language :: Cython
Classifier: Programming Language :: Python :: Implementation :: CPython
Classifier: Topic :: Scientific/Engineering
Classifier: Topic :: Scientific/Engineering :: Astronomy
Classifier: Topic :: Scientific/Engineering :: Atmospheric Science
Classifier: Topic :: Scientific/Engineering :: Physics
Requires-Python: >=3.8
License-File: LICENSE
Requires-Dist: numpy <2.0
Requires-Dist: scipy >=1.6
Provides-Extra: coverage
Requires-Dist: Cython ; extra == 'coverage'
Requires-Dist: pytest-cov ; extra == 'coverage'
Provides-Extra: docs
Requires-Dist: matplotlib ; extra == 'docs'
Requires-Dist: sphinx ; extra == 'docs'
Provides-Extra: io
Requires-Dist: h5py ; extra == 'io'
Provides-Extra: test
Requires-Dist: pytest ; extra == 'test'
